defisocket/__init__.py
defisocket/block_stream.py
defisocket/event_stream.py
defisocket/models.py
defisocket/cli/historical.py
defisocket/cli/live.py
defisocket/event_models/aave.py
defisocket/event_models/base.py
defisocket/event_models/staking.py
defisocket/event_models/uniswap.py
defisocket-1.6.0.dist-info/licenses/LICENSE
defisocket-1.6.0.dist-info/METADATA
defisocket-1.6.0.dist-info/WHEEL
defisocket-1.6.0.dist-info/top_level.txt
defisocket-1.6.0.dist-info/RECORD
