Metadata-Version: 2.4
Name: defisocket
Version: 1.6.0
Summary: Ofiicial Python SDK for the DefiSocket API, providing easy access to DeFi data and functionalities.
Author-email: Eren Nevin <eren.m.nevin@gmail.com>
License: MIT
Project-URL: Homepage, https://defisocket.com
Requires-Python: >=3.10
License-File: LICENSE
Requires-Dist: requests>=2
Requires-Dist: python-dotenv>=1
Requires-Dist: websockets>=14
Dynamic: license-file
